ros_introspect/__init__.py
ros_introspect/_version.py
ros_introspect/finder.py
ros_introspect/package.py
ros_introspect/ros_resources.py
ros_introspect/util.py
ros_introspect/components/cmake.py
ros_introspect/components/documentation.py
ros_introspect/components/dynamic_reconfig.py
ros_introspect/components/launch.py
ros_introspect/components/misc_config.py
ros_introspect/components/package_xml.py
ros_introspect/components/param_config.py
ros_introspect/components/plugin_xml.py
ros_introspect/components/ros_interface.py
ros_introspect/components/rviz_config.py
ros_introspect/components/setup_cfg.py
ros_introspect/components/setup_py.py
ros_introspect/components/source_code.py
ros_introspect/components/urdf.py
ros_introspect-0.3.0.dist-info/METADATA
ros_introspect-0.3.0.dist-info/WHEEL
ros_introspect-0.3.0.dist-info/licenses/LICENSE
ros_introspect-0.3.0.dist-info/RECORD
